README.md
setup.cfg
setup.py
service_flower/__init__.py
service_flower/client.py
service_flower/conf.py
service_flower/exceptions.py
service_flower/models.py
service_flower/states.py
service_flower.egg-info/PKG-INFO
service_flower.egg-info/SOURCES.txt
service_flower.egg-info/dependency_links.txt
service_flower.egg-info/not-zip-safe
service_flower.egg-info/requires.txt
service_flower.egg-info/top_level.txt